kagiso_wagtail_slack/__init__.py
kagiso_wagtail_slack/apps.py
kagiso_wagtail_slack/handlers.py
kagiso_wagtail_slack-2.0.0.dist-info/DESCRIPTION.rst
kagiso_wagtail_slack-2.0.0.dist-info/METADATA
kagiso_wagtail_slack-2.0.0.dist-info/metadata.json
kagiso_wagtail_slack-2.0.0.dist-info/RECORD
kagiso_wagtail_slack-2.0.0.dist-info/top_level.txt
kagiso_wagtail_slack-2.0.0.dist-info/WHEEL
