Metadata-Version: 2.0
Name: kagiso-wagtail-slack
Version: 2.0.0
Summary: Kagiso Wagtail Slack
Home-page: https://github.com/Kagiso-Future-Media/kagiso_wagtail_slack
Author: Kagiso Media
Author-email: development@kagiso.io
License: UNKNOWN
Platform: UNKNOWN
Requires-Dist: wagtail (>=1.8.0)
